vilo.py
vilo-0.0.5.dist-info/LICENSE.txt
vilo-0.0.5.dist-info/WHEEL
vilo-0.0.5.dist-info/METADATA
vilo-0.0.5.dist-info/RECORD
