Metadata-Version: 2.1
Name: vilo
Version: 0.0.5
Summary: Vilo: Simple, unopinionated Python web framework.
Home-page: https://github.com/polydojo/vilo
License: UNKNOWN
Author: Polydojo, Inc.
Author-email: 8079593+sumukhbarve@users.noreply.github.com
Classifier: License :: OSI Approved :: Apache Software License
Requires-Dist: dotsi >=0.0.3
